robottelo/__init__.py
robottelo/bz_helpers.py
robottelo/cleanup.py
robottelo/constants.py
robottelo/datafactory.py
robottelo/helpers.py
robottelo/host_info.py
robottelo/libvirt_discovery.py
robottelo/log.py
robottelo/manifests.py
robottelo/products.py
robottelo/ssh.py
robottelo/system_facts.py
robottelo/test.py
robottelo/vm.py
robottelo/vm_capsule.py
robottelo/api/__init__.py
robottelo/api/assertions.py
robottelo/api/utils.py
robottelo/cli/__init__.py
robottelo/cli/activationkey.py
robottelo/cli/architecture.py
robottelo/cli/assertions.py
robottelo/cli/auth.py
robottelo/cli/base.py
robottelo/cli/capsule.py
robottelo/cli/computeresource.py
robottelo/cli/contentview.py
robottelo/cli/csv_.py
robottelo/cli/defaults.py
robottelo/cli/discoveredhost.py
robottelo/cli/discoveryrule.py
robottelo/cli/docker.py
robottelo/cli/domain.py
robottelo/cli/environment.py
robottelo/cli/erratum.py
robottelo/cli/fact.py
robottelo/cli/factory.py
robottelo/cli/file.py
robottelo/cli/filter.py
robottelo/cli/globalparam.py
robottelo/cli/gpgkey.py
robottelo/cli/hammer.py
robottelo/cli/host.py
robottelo/cli/hostcollection.py
robottelo/cli/hostgroup.py
robottelo/cli/job_invocation.py
robottelo/cli/job_template.py
robottelo/cli/ldapauthsource.py
robottelo/cli/lifecycleenvironment.py
robottelo/cli/location.py
robottelo/cli/medium.py
robottelo/cli/model.py
robottelo/cli/operatingsys.py
robottelo/cli/org.py
robottelo/cli/ostreebranch.py
robottelo/cli/package.py
robottelo/cli/partitiontable.py
robottelo/cli/product.py
robottelo/cli/proxy.py
robottelo/cli/puppet.py
robottelo/cli/puppetmodule.py
robottelo/cli/realm.py
robottelo/cli/recurring_logic.py
robottelo/cli/report.py
robottelo/cli/repository.py
robottelo/cli/repository_set.py
robottelo/cli/role.py
robottelo/cli/scap_policy.py
robottelo/cli/scap_tailoring_files.py
robottelo/cli/scapcontent.py
robottelo/cli/scparams.py
robottelo/cli/settings.py
robottelo/cli/smart_variable.py
robottelo/cli/subnet.py
robottelo/cli/subscription.py
robottelo-0.1.0.dist-info/LICENSE
robottelo-0.1.0.dist-info/METADATA
robottelo-0.1.0.dist-info/WHEEL
robottelo-0.1.0.dist-info/top_level.txt
robottelo-0.1.0.dist-info/RECORD
