Metadata-Version: 2.1
Name: robottelo
Version: 0.1.0
Summary: Robottelo is a test suite which exercises The Foreman.
Home-page: https://github.com/SatelliteQE/robottelo
Author: Satellite QE Team
Author-email: UNKNOWN
License: GNU GPL v3.0
Platform: UNKNOWN
Classifier: Development Status :: 5 - Production/Stable
Classifier: Intended Audience :: Developers
Classifier: License :: OSI Approved :: GNU General Public License v3 (GPLv3)
Classifier: Natural Language :: English
Classifier: Operating System :: POSIX :: Linux
Classifier: Programming Language :: Python :: 3
